dtocean_moorings/__init__.py
dtocean_moorings-2.1.0.dist-info/METADATA
dtocean_moorings-2.1.0.dist-info/WHEEL
dtocean_moorings-2.1.0.dist-info/RECORD
